meshcheck/__init__.py
meshcheck/__main__.py
meshcheck/angle.py
meshcheck/app.py
meshcheck/camera.py
meshcheck/camera_controller.py
meshcheck/events.py
meshcheck/shader.py
meshcheck/text_render.py
meshcheck/util.py
meshcheck/window.py
meshcheck/shaders/basic.frag.glsl
meshcheck/shaders/basic.vert.glsl
meshcheck/shaders/default.frag.glsl
meshcheck/shaders/default.geom.glsl
meshcheck/shaders/default.vert.glsl
meshcheck/shaders/text.frag.glsl
meshcheck/shaders/text.vert.glsl
meshcheck-1.7.0.data/scripts/meshcheck
meshcheck-1.7.0.dist-info/DESCRIPTION.rst
meshcheck-1.7.0.dist-info/METADATA
meshcheck-1.7.0.dist-info/RECORD
meshcheck-1.7.0.dist-info/WHEEL
meshcheck-1.7.0.dist-info/metadata.json
meshcheck-1.7.0.dist-info/top_level.txt
