Metadata-Version: 2.0
Name: meshcheck
Version: 1.7.0
Summary: Simple 3D mesh visualization tool
Home-page: https://github.com/nicholasbishop/meshcheck
Author: Nicholas Bishop
Author-email: nicholasbishop@gmail.com
License: UNKNOWN
Platform: UNKNOWN
Requires-Dist: attrs (~=17.3.0)
Requires-Dist: glfw (~=1.4.0)
Requires-Dist: glm (~=0.1.0)
Requires-Dist: ModernGL (~=4.2.1)
Requires-Dist: pycairo (~=1.11.1)
Requires-Dist: PyGLM (~=0.2.1a1)
Requires-Dist: PyGObject (~=3.27.1)
